pop/README.md
pop/__init__.py
pop/config.py
pop/efficient_frontier.py
pop/models.py
pop/scipy_interface.py
pop/transforms.py
proteusllp_optimisation_package-0.1.3.dist-info/METADATA
proteusllp_optimisation_package-0.1.3.dist-info/WHEEL
proteusllp_optimisation_package-0.1.3.dist-info/entry_points.txt
proteusllp_optimisation_package-0.1.3.dist-info/licenses/LICENSE
proteusllp_optimisation_package-0.1.3.dist-info/RECORD
