Metadata-Version: 2.1
Name: proteusllp-optimisation-package
Version: 0.1.3
Summary: Proteus Optimisation Package (POP): Domain-agnostic stochastic optimization engine for PAL variables
Keywords: optimization,stochastic,portfolio,risk-analysis,PAL,actuarial
Author-Email: Proteus LLP <info@proteusllp.com>
Maintainer-Email: Proteus LLP <info@proteusllp.com>
License: MIT License
Classifier: Development Status :: 3 - Alpha
Classifier: Intended Audience :: Financial and Insurance Industry
Classifier: Intended Audience :: Science/Research
Classifier: License :: OSI Approved :: MIT License
Classifier: Programming Language :: Python :: 3
Classifier: Programming Language :: Python :: 3.13
Classifier: Topic :: Scientific/Engineering :: Mathematics
Classifier: Topic :: Office/Business :: Financial
Project-URL: Homepage, https://github.com/ProteusLLP/proteusllp-optimisation-package
Project-URL: Repository, https://github.com/ProteusLLP/proteusllp-optimisation-package
Project-URL: Issues, https://github.com/ProteusLLP/proteusllp-optimisation-package/issues
Project-URL: Documentation, https://proteusllp-optimisation-package.readthedocs.io/
Requires-Python: >=3.13
Requires-Dist: proteusllp-actuarial-library>=0.2.8
Requires-Dist: numpy>=2.2
Requires-Dist: scipy>=1.15
Requires-Dist: pydantic>=2.0
Requires-Dist: cvxopt
Provides-Extra: docs
Requires-Dist: sphinx>=8.2.3; extra == "docs"
Requires-Dist: sphinx-rtd-theme>=3.0.2; extra == "docs"
Requires-Dist: myst-parser>=4.0.1; extra == "docs"
Requires-Dist: sphinx-autodoc-typehints>=3.5.2; extra == "docs"
